enrobie/__init__.py
enrobie/conftest.py
enrobie/py.typed
enrobie/version.txt
enrobie/clients/__init__.py
enrobie/clients/discord/__init__.py
enrobie/clients/discord/client.py
enrobie/clients/discord/command.py
enrobie/clients/discord/message.py
enrobie/clients/discord/params.py
enrobie/clients/discord/test/__init__.py
enrobie/clients/discord/test/test_client.py
enrobie/clients/discord/test/test_command.py
enrobie/clients/discord/test/test_message.py
enrobie/clients/irc/__init__.py
enrobie/clients/irc/client.py
enrobie/clients/irc/command.py
enrobie/clients/irc/message.py
enrobie/clients/irc/params.py
enrobie/clients/irc/states.py
enrobie/clients/irc/test/__init__.py
enrobie/clients/irc/test/test_client.py
enrobie/clients/irc/test/test_command.py
enrobie/clients/irc/test/test_message.py
enrobie/clients/mattermost/__init__.py
enrobie/clients/mattermost/client.py
enrobie/clients/mattermost/command.py
enrobie/clients/mattermost/message.py
enrobie/clients/mattermost/params.py
enrobie/clients/mattermost/test/__init__.py
enrobie/clients/mattermost/test/test_client.py
enrobie/clients/mattermost/test/test_command.py
enrobie/clients/mattermost/test/test_message.py
enrobie/execution/__init__.py
enrobie/execution/config.py
enrobie/execution/crypts.py
enrobie/execution/service.py
enrobie/execution/test/__init__.py
enrobie/execution/test/test_config.py
enrobie/execution/test/test_crypts.py
enrobie/execution/test/test_service.py
enrobie/plugins/__init__.py
enrobie/plugins/ainswer/__init__.py
enrobie/plugins/ainswer/ainswer.py
enrobie/plugins/ainswer/common.py
enrobie/plugins/ainswer/helpers.py
enrobie/plugins/ainswer/history.py
enrobie/plugins/ainswer/memory.py
enrobie/plugins/ainswer/models.py
enrobie/plugins/ainswer/params.py
enrobie/plugins/ainswer/plugin.py
enrobie/plugins/ainswer/question.py
enrobie/plugins/ainswer/toolset.py
enrobie/plugins/ainswer/test/__init__.py
enrobie/plugins/ainswer/test/test_history.py
enrobie/plugins/ainswer/test/test_memory.py
enrobie-0.14.7.dist-info/licenses/LICENSE
enrobie-0.14.7.dist-info/METADATA
enrobie-0.14.7.dist-info/WHEEL
enrobie-0.14.7.dist-info/top_level.txt
enrobie-0.14.7.dist-info/RECORD
