Metadata-Version: 2.4
Name: enrobie
Version: 0.14.7
Summary: Enasis Network Chatting Robie
License: MIT
Project-URL: Source, https://github.com/enasisnetwork/enrobie
Project-URL: Documentation, https://enasisnetwork.github.io/enrobie/sphinx
Classifier: Programming Language :: Python :: 3
Classifier: Programming Language :: Python :: 3.11
Classifier: Programming Language :: Python :: 3.12
Requires-Python: >=3.11
License-File: LICENSE
Requires-Dist: encommon>=0.22.11
Requires-Dist: enconnect>=0.17.18
Requires-Dist: enhomie>=0.13.10
Dynamic: license-file
